locus_processing/__init__.py
locus_processing/cli.py
locus_processing/lookups.py
locus_processing/models.py
locus_processing/schemas.py
locus_processing/utils.py
locus_processing-0.0.4.dist-info/LICENSE
locus_processing-0.0.4.dist-info/METADATA
locus_processing-0.0.4.dist-info/WHEEL
locus_processing-0.0.4.dist-info/entry_points.txt
locus_processing-0.0.4.dist-info/top_level.txt
locus_processing-0.0.4.dist-info/RECORD
